isql_kernel/__init__.py
isql_kernel/__main__.py
isql_kernel/install.py
isql_kernel/isql_kernel_config.py
isql_kernel/kernel.py
isql_kernel/magics.py
isql_kernel/kernelspec/kernel.js
isql_kernel/kernelspec/logo-64x64.png
venv/share/jupyter/kernels/isql_kernel/kernel.js
venv/share/jupyter/kernels/isql_kernel/kernel.json
venv/share/jupyter/kernels/isql_kernel/logo-64x64.png
venv/share/jupyter/kernels/python3/kernel.json
venv/share/jupyter/kernels/python3/logo-32x32.png
venv/share/jupyter/kernels/python3/logo-64x64.png
isql_kernel-1.0.7.dist-info/METADATA
isql_kernel-1.0.7.dist-info/WHEEL
isql_kernel-1.0.7.dist-info/top_level.txt
isql_kernel-1.0.7.dist-info/RECORD
