Metadata-Version: 2.4
Name: isql_kernel
Version: 1.0.7
Summary: Extensible Jupyter kernel for ISQL
Author: Shanmukh raj MSS
Project-URL: Homepage, https://github.com/ShanmukhEstrella/ISQL-Jupyter
Classifier: Programming Language :: Python :: 3
Classifier: License :: OSI Approved :: MIT License
Classifier: Operating System :: OS Independent
Classifier: Intended Audience :: Developers
Requires-Python: >=3.7
Requires-Dist: jupyter_client
Requires-Dist: IPython
Requires-Dist: ipykernel
Requires-Dist: graphviz
Requires-Dist: beautifulsoup4
Requires-Dist: sqlparse
Requires-Dist: pandas
